<?xml version="1.0" encoding="UTF-8" standalone="no"?>
<graphml xmlns="http://graphml.graphdrawing.org/xmlns" xmlns:java="http://www.yworks.com/xml/yfiles-common/1.0/java" xmlns:sys="http://www.yworks.com/xml/yfiles-common/markup/primitives/2.0" xmlns:x="http://www.yworks.com/xml/yfiles-common/markup/2.0" xmlns:xsi="http://www.w3.org/2001/XMLSchema-instance" xmlns:y="http://www.yworks.com/xml/graphml" xmlns:yed="http://www.yworks.com/xml/yed/3" xsi:schemaLocation="http://graphml.graphdrawing.org/xmlns http://www.yworks.com/xml/schema/graphml/1.1/ygraphml.xsd">
  <!--Created by yEd 3.21.1-->
  <key attr.name="Description" attr.type="string" for="graph" id="d0"/>
  <key for="port" id="d1" yfiles.type="portgraphics"/>
  <key for="port" id="d2" yfiles.type="portgeometry"/>
  <key for="port" id="d3" yfiles.type="portuserdata"/>
  <key attr.name="url" attr.type="string" for="node" id="d4"/>
  <key attr.name="description" attr.type="string" for="node" id="d5"/>
  <key for="node" id="d6" yfiles.type="nodegraphics"/>
  <key for="graphml" id="d7" yfiles.type="resources"/>
  <key attr.name="url" attr.type="string" for="edge" id="d8"/>
  <key attr.name="description" attr.type="string" for="edge" id="d9"/>
  <key for="edge" id="d10" yfiles.type="edgegraphics"/>
  <graph edgedefault="directed" id="G">
    <data key="d0"/>
    <node id="n0">
      <data key="d6">
        <y:GenericNode configuration="com.yworks.bpmn.Event.withShadow">
          <y:Geometry height="30.0" width="30.0" x="70.6666666666666" y="116.0"/>
          <y:Fill color="#000000" color2="#000000" transparent="false"/>
          <y:BorderStyle color="#000000" type="line" width="1.0"/>
          <y:NodeLabel alignment="center" autoSizePolicy="content" fontFamily="Dialog" fontSize="12" fontStyle="plain" hasBackgroundColor="false" hasLineColor="false" hasText="false" height="4.0" horizontalTextPosition="center" iconTextGap="4" modelName="custom" textColor="#000000" verticalTextPosition="bottom" visible="true" width="4.0" x="13.0" y="34.0">
            <y:LabelModel>
              <y:SmartNodeLabelModel distance="4.0"/>
            </y:LabelModel>
            <y:ModelParameter>
              <y:SmartNodeLabelModelParameter labelRatioX="0.0" labelRatioY="-0.5" nodeRatioX="0.0" nodeRatioY="0.5" offsetX="0.0" offsetY="4.0" upX="0.0" upY="-1.0"/>
            </y:ModelParameter>
          </y:NodeLabel>
          <y:StyleProperties>
            <y:Property class="com.yworks.yfiles.bpmn.view.EventCharEnum" name="com.yworks.bpmn.characteristic" value="EVENT_CHARACTERISTIC_START"/>
            <y:Property class="java.awt.Color" name="com.yworks.bpmn.icon.line.color" value="#000000"/>
            <y:Property class="java.awt.Color" name="com.yworks.bpmn.icon.fill2" value="#d4d4d4cc"/>
            <y:Property class="java.awt.Color" name="com.yworks.bpmn.icon.fill" value="#ffffffe6"/>
            <y:Property class="com.yworks.yfiles.bpmn.view.BPMNTypeEnum" name="com.yworks.bpmn.type" value="EVENT_TYPE_PLAIN"/>
          </y:StyleProperties>
        </y:GenericNode>
      </data>
    </node>
    <node id="n1">
      <data key="d6">
        <y:GenericNode configuration="com.yworks.sbgn.Macromolecule">
          <y:Geometry height="40.0" width="80.0" x="237.33333333333326" y="111.0"/>
          <y:Fill color="#FFFFFF" transparent="false"/>
          <y:BorderStyle color="#000000" type="line" width="1.0"/>
          <y:NodeLabel alignment="center" autoSizePolicy="content" fontFamily="Dialog" fontSize="12" fontStyle="plain" hasBackgroundColor="false" hasLineColor="false" height="18.701171875" horizontalTextPosition="center" iconTextGap="4" modelName="custom" textColor="#000000" verticalTextPosition="center" visible="true" width="38.01953125" x="20.990234375" xml:space="preserve" y="10.6494140625">Attesa<y:LabelModel><y:SmartNodeLabelModel distance="4.0"/></y:LabelModel><y:ModelParameter><y:SmartNodeLabelModelParameter labelRatioX="0.0" labelRatioY="0.0" nodeRatioX="0.0" nodeRatioY="0.0" offsetX="0.0" offsetY="0.0" upX="0.0" upY="-1.0"/></y:ModelParameter></y:NodeLabel>
          <y:StyleProperties>
            <y:Property class="java.lang.Integer" name="com.yworks.sbgn.style.radius" value="10"/>
          </y:StyleProperties>
        </y:GenericNode>
      </data>
    </node>
    <node id="n2">
      <data key="d6">
        <y:GenericNode configuration="com.yworks.sbgn.Macromolecule">
          <y:Geometry height="40.0" width="80.0" x="237.33333333333326" y="233.0"/>
          <y:Fill color="#FFFFFF" transparent="false"/>
          <y:BorderStyle color="#000000" type="line" width="1.0"/>
          <y:NodeLabel alignment="center" autoSizePolicy="content" fontFamily="Dialog" fontSize="12" fontStyle="plain" hasBackgroundColor="false" hasLineColor="false" height="18.701171875" horizontalTextPosition="center" iconTextGap="4" modelName="custom" textColor="#000000" verticalTextPosition="center" visible="true" width="56.705078125" x="11.6474609375" xml:space="preserve" y="10.6494140625">Selezione<y:LabelModel><y:SmartNodeLabelModel distance="4.0"/></y:LabelModel><y:ModelParameter><y:SmartNodeLabelModelParameter labelRatioX="0.0" labelRatioY="0.0" nodeRatioX="0.0" nodeRatioY="0.0" offsetX="0.0" offsetY="0.0" upX="0.0" upY="-1.0"/></y:ModelParameter></y:NodeLabel>
          <y:StyleProperties>
            <y:Property class="java.lang.Integer" name="com.yworks.sbgn.style.radius" value="10"/>
          </y:StyleProperties>
        </y:GenericNode>
      </data>
    </node>
    <node id="n3">
      <data key="d6">
        <y:GenericNode configuration="com.yworks.sbgn.Macromolecule">
          <y:Geometry height="40.0" width="80.0" x="472.9999999999998" y="233.0"/>
          <y:Fill color="#FFFFFF" transparent="false"/>
          <y:BorderStyle color="#000000" type="line" width="1.0"/>
          <y:NodeLabel alignment="center" autoSizePolicy="content" fontFamily="Dialog" fontSize="12" fontStyle="plain" hasBackgroundColor="false" hasLineColor="false" height="33.40234375" horizontalTextPosition="center" iconTextGap="4" modelName="custom" textColor="#000000" verticalTextPosition="center" visible="true" width="65.376953125" x="7.3115234375" xml:space="preserve" y="3.298828125">Pagamento
in moneta<y:LabelModel><y:SmartNodeLabelModel distance="4.0"/></y:LabelModel><y:ModelParameter><y:SmartNodeLabelModelParameter labelRatioX="0.0" labelRatioY="0.0" nodeRatioX="0.0" nodeRatioY="0.0" offsetX="0.0" offsetY="0.0" upX="0.0" upY="-1.0"/></y:ModelParameter></y:NodeLabel>
          <y:StyleProperties>
            <y:Property class="java.lang.Integer" name="com.yworks.sbgn.style.radius" value="10"/>
          </y:StyleProperties>
        </y:GenericNode>
      </data>
    </node>
    <node id="n4">
      <data key="d6">
        <y:GenericNode configuration="com.yworks.bpmn.Gateway.withShadow">
          <y:Geometry height="45.0" width="45.0" x="490.4999999999998" y="108.5"/>
          <y:Fill color="#FFFFFFE6" color2="#D4D4D4CC" transparent="false"/>
          <y:BorderStyle color="#E38B00" type="line" width="1.0"/>
          <y:NodeLabel alignment="center" autoSizePolicy="content" fontFamily="Dialog" fontSize="12" fontStyle="plain" hasBackgroundColor="false" hasLineColor="false" hasText="false" height="4.0" horizontalTextPosition="center" iconTextGap="4" modelName="custom" textColor="#000000" verticalTextPosition="bottom" visible="true" width="4.0" x="49.0" y="-8.0">
            <y:LabelModel>
              <y:SmartNodeLabelModel distance="4.0"/>
            </y:LabelModel>
            <y:ModelParameter>
              <y:SmartNodeLabelModelParameter labelRatioX="-0.5" labelRatioY="0.5" nodeRatioX="0.5" nodeRatioY="-0.5" offsetX="4.0" offsetY="-4.0" upX="0.0" upY="-1.0"/>
            </y:ModelParameter>
          </y:NodeLabel>
          <y:StyleProperties>
            <y:Property class="java.awt.Color" name="com.yworks.bpmn.icon.line.color" value="#000000"/>
            <y:Property class="java.awt.Color" name="com.yworks.bpmn.icon.fill2" value="#d4d4d4cc"/>
            <y:Property class="java.awt.Color" name="com.yworks.bpmn.icon.fill" value="#ffffffe6"/>
            <y:Property class="com.yworks.yfiles.bpmn.view.BPMNTypeEnum" name="com.yworks.bpmn.type" value="GATEWAY_TYPE_PLAIN"/>
          </y:StyleProperties>
        </y:GenericNode>
      </data>
    </node>
    <node id="n5">
      <data key="d6">
        <y:GenericNode configuration="com.yworks.bpmn.Gateway.withShadow">
          <y:Geometry height="45.0" width="45.0" x="254.83333333333326" y="374.0"/>
          <y:Fill color="#FFFFFFE6" color2="#D4D4D4CC" transparent="false"/>
          <y:BorderStyle color="#E38B00" type="line" width="1.0"/>
          <y:NodeLabel alignment="center" autoSizePolicy="content" fontFamily="Dialog" fontSize="12" fontStyle="plain" hasBackgroundColor="false" hasLineColor="false" hasText="false" height="4.0" horizontalTextPosition="center" iconTextGap="4" modelName="custom" textColor="#000000" verticalTextPosition="bottom" visible="true" width="4.0" x="49.0" y="-8.0">
            <y:LabelModel>
              <y:SmartNodeLabelModel distance="4.0"/>
            </y:LabelModel>
            <y:ModelParameter>
              <y:SmartNodeLabelModelParameter labelRatioX="-0.5" labelRatioY="0.5" nodeRatioX="0.5" nodeRatioY="-0.5" offsetX="4.0" offsetY="-4.0" upX="0.0" upY="-1.0"/>
            </y:ModelParameter>
          </y:NodeLabel>
          <y:StyleProperties>
            <y:Property class="java.awt.Color" name="com.yworks.bpmn.icon.line.color" value="#000000"/>
            <y:Property class="java.awt.Color" name="com.yworks.bpmn.icon.fill2" value="#d4d4d4cc"/>
            <y:Property class="java.awt.Color" name="com.yworks.bpmn.icon.fill" value="#ffffffe6"/>
            <y:Property class="com.yworks.yfiles.bpmn.view.BPMNTypeEnum" name="com.yworks.bpmn.type" value="GATEWAY_TYPE_PLAIN"/>
          </y:StyleProperties>
        </y:GenericNode>
      </data>
    </node>
    <edge id="e0" source="n0" target="n1">
      <data key="d8" xml:space="preserve"/>
      <data key="d9"/>
      <data key="d10">
        <y:PolyLineEdge>
          <y:Path sx="0.0" sy="0.0" tx="0.0" ty="0.0"/>
          <y:LineStyle color="#000000" type="line" width="1.0"/>
          <y:Arrows source="none" target="delta"/>
          <y:BendStyle smoothed="false"/>
        </y:PolyLineEdge>
      </data>
    </edge>
    <edge id="e1" source="n1" target="n2">
      <data key="d8" xml:space="preserve"/>
      <data key="d9"/>
      <data key="d10">
        <y:PolyLineEdge>
          <y:Path sx="0.0" sy="0.0" tx="0.0" ty="0.0"/>
          <y:LineStyle color="#000000" type="line" width="1.0"/>
          <y:Arrows source="none" target="delta"/>
          <y:EdgeLabel alignment="center" configuration="AutoFlippingLabel" distance="2.0" fontFamily="Dialog" fontSize="12" fontStyle="plain" hasBackgroundColor="false" hasLineColor="false" height="18.701171875" horizontalTextPosition="center" iconTextGap="4" modelName="custom" preferredPlacement="anywhere" ratio="0.5" textColor="#000000" verticalTextPosition="bottom" visible="true" width="66.033203125" x="-74.01661173502609" xml:space="preserve" y="24.66357421875">uso tastiera<y:LabelModel><y:SmartEdgeLabelModel autoRotationEnabled="false" defaultAngle="0.0" defaultDistance="10.0"/></y:LabelModel><y:ModelParameter><y:SmartEdgeLabelModelParameter angle="6.283185307179586" distance="40.99999999999997" distanceToCenter="true" position="right" ratio="0.3686650298655136" segment="-1"/></y:ModelParameter><y:PreferredPlacementDescriptor angle="0.0" angleOffsetOnRightSide="0" angleReference="absolute" angleRotationOnRightSide="co" distance="-1.0" frozen="true" placement="anywhere" side="anywhere" sideReference="relative_to_edge_flow"/></y:EdgeLabel>
          <y:BendStyle smoothed="false"/>
        </y:PolyLineEdge>
      </data>
    </edge>
    <edge id="e2" source="n2" target="n2">
      <data key="d8" xml:space="preserve"/>
      <data key="d9"/>
      <data key="d10">
        <y:PolyLineEdge>
          <y:Path sx="0.0" sy="0.0" tx="0.0" ty="0.0">
            <y:Point x="204.33333333333326" y="253.0"/>
          </y:Path>
          <y:LineStyle color="#000000" type="line" width="1.0"/>
          <y:Arrows source="none" target="delta"/>
          <y:EdgeLabel alignment="center" configuration="AutoFlippingLabel" distance="2.0" fontFamily="Dialog" fontSize="12" fontStyle="plain" hasBackgroundColor="false" hasLineColor="false" height="18.701171875" horizontalTextPosition="center" iconTextGap="4" modelName="custom" preferredPlacement="anywhere" ratio="0.5" textColor="#000000" verticalTextPosition="bottom" visible="true" width="85.380859375" x="-160.44962565104174" xml:space="preserve" y="2.6572265625">pressione tasto<y:LabelModel><y:SmartEdgeLabelModel autoRotationEnabled="false" defaultAngle="0.0" defaultDistance="10.0"/></y:LabelModel><y:ModelParameter><y:SmartEdgeLabelModelParameter angle="6.283185307179586" distance="8.0" distanceToCenter="true" position="right" ratio="50.75" segment="-2"/></y:ModelParameter><y:PreferredPlacementDescriptor angle="0.0" angleOffsetOnRightSide="0" angleReference="absolute" angleRotationOnRightSide="co" distance="-1.0" frozen="true" placement="anywhere" side="anywhere" sideReference="relative_to_edge_flow"/></y:EdgeLabel>
          <y:BendStyle smoothed="false"/>
        </y:PolyLineEdge>
      </data>
    </edge>
    <edge id="e3" source="n2" target="n3">
      <data key="d8" xml:space="preserve"/>
      <data key="d9"/>
      <data key="d10">
        <y:PolyLineEdge>
          <y:Path sx="0.0" sy="0.0" tx="0.0" ty="0.0"/>
          <y:LineStyle color="#000000" type="line" width="1.0"/>
          <y:Arrows source="none" target="delta"/>
          <y:EdgeLabel alignment="center" configuration="AutoFlippingLabel" distance="2.0" fontFamily="Dialog" fontSize="12" fontStyle="plain" hasBackgroundColor="false" hasLineColor="false" height="18.701171875" horizontalTextPosition="center" iconTextGap="4" modelName="custom" preferredPlacement="anywhere" ratio="0.5" textColor="#000000" verticalTextPosition="bottom" visible="true" width="109.38671875" x="18.23871683695853" xml:space="preserve" y="-24.3505859375">inserimento moneta<y:LabelModel><y:SmartEdgeLabelModel autoRotationEnabled="false" defaultAngle="0.0" defaultDistance="10.0"/></y:LabelModel><y:ModelParameter><y:SmartEdgeLabelModelParameter angle="6.283185307179586" distance="15.0" distanceToCenter="true" position="left" ratio="0.36534977499853805" segment="-1"/></y:ModelParameter><y:PreferredPlacementDescriptor angle="0.0" angleOffsetOnRightSide="0" angleReference="absolute" angleRotationOnRightSide="co" distance="-1.0" frozen="true" placement="anywhere" side="anywhere" sideReference="relative_to_edge_flow"/></y:EdgeLabel>
          <y:BendStyle smoothed="false"/>
        </y:PolyLineEdge>
      </data>
    </edge>
    <edge id="e4" source="n3" target="n3">
      <data key="d8" xml:space="preserve"/>
      <data key="d9"/>
      <data key="d10">
        <y:PolyLineEdge>
          <y:Path sx="0.0" sy="0.0" tx="0.0" ty="0.0">
            <y:Point x="512.9999999999998" y="309.0"/>
          </y:Path>
          <y:LineStyle color="#000000" type="line" width="1.0"/>
          <y:Arrows source="none" target="delta"/>
          <y:EdgeLabel alignment="center" configuration="AutoFlippingLabel" distance="2.0" fontFamily="Dialog" fontSize="12" fontStyle="plain" hasBackgroundColor="false" hasLineColor="false" height="18.701171875" horizontalTextPosition="center" iconTextGap="4" modelName="custom" preferredPlacement="anywhere" ratio="0.5" textColor="#000000" verticalTextPosition="bottom" visible="true" width="178.767578125" x="-51.6791687011721" xml:space="preserve" y="42.308197021484375">moneta inserita, aggiorna credito<y:LabelModel><y:SmartEdgeLabelModel autoRotationEnabled="false" defaultAngle="0.0" defaultDistance="10.0"/></y:LabelModel><y:ModelParameter><y:SmartEdgeLabelModelParameter angle="6.283185307179586" distance="11.0" distanceToCenter="true" position="right" ratio="-15.67529296875" segment="-1"/></y:ModelParameter><y:PreferredPlacementDescriptor angle="0.0" angleOffsetOnRightSide="0" angleReference="absolute" angleRotationOnRightSide="co" distance="-1.0" frozen="true" placement="anywhere" side="anywhere" sideReference="relative_to_edge_flow"/></y:EdgeLabel>
          <y:BendStyle smoothed="false"/>
        </y:PolyLineEdge>
      </data>
    </edge>
    <edge id="e5" source="n3" target="n4">
      <data key="d8" xml:space="preserve"/>
      <data key="d9"/>
      <data key="d10">
        <y:PolyLineEdge>
          <y:Path sx="0.0" sy="0.0" tx="0.0" ty="0.0"/>
          <y:LineStyle color="#000000" type="line" width="1.0"/>
          <y:Arrows source="none" target="delta"/>
          <y:EdgeLabel alignment="center" configuration="AutoFlippingLabel" distance="2.0" fontFamily="Dialog" fontSize="12" fontStyle="plain" hasBackgroundColor="false" hasLineColor="false" height="18.701171875" horizontalTextPosition="center" iconTextGap="4" modelName="custom" preferredPlacement="anywhere" ratio="0.5" textColor="#000000" verticalTextPosition="bottom" visible="true" width="182.107421875" x="4.946289062499773" xml:space="preserve" y="-35.19502439185007">credito sufficiente, eroga prodotto<y:LabelModel><y:SmartEdgeLabelModel autoRotationEnabled="false" defaultAngle="0.0" defaultDistance="10.0"/></y:LabelModel><y:ModelParameter><y:SmartEdgeLabelModelParameter angle="6.283185307179586" distance="96.0" distanceToCenter="true" position="right" ratio="0.225983409151726" segment="-1"/></y:ModelParameter><y:PreferredPlacementDescriptor angle="0.0" angleOffsetOnRightSide="0" angleReference="absolute" angleRotationOnRightSide="co" distance="-1.0" frozen="true" placement="anywhere" side="anywhere" sideReference="relative_to_edge_flow"/></y:EdgeLabel>
          <y:BendStyle smoothed="false"/>
        </y:PolyLineEdge>
      </data>
    </edge>
    <edge id="e6" source="n4" target="n1">
      <data key="d8" xml:space="preserve"/>
      <data key="d9"/>
      <data key="d10">
        <y:PolyLineEdge>
          <y:Path sx="0.0" sy="0.0" tx="0.0" ty="0.0">
            <y:Point x="414.0" y="163.0"/>
          </y:Path>
          <y:LineStyle color="#000000" type="line" width="1.0"/>
          <y:Arrows source="none" target="delta"/>
          <y:EdgeLabel alignment="center" configuration="AutoFlippingLabel" distance="2.0" fontFamily="Dialog" fontSize="12" fontStyle="plain" hasBackgroundColor="false" hasLineColor="false" height="18.701171875" horizontalTextPosition="center" iconTextGap="4" modelName="custom" preferredPlacement="anywhere" ratio="0.5" textColor="#000000" verticalTextPosition="bottom" visible="true" width="47.359375" x="-109.32174169810384" xml:space="preserve" y="35.555051600912634">no resto<y:LabelModel><y:SmartEdgeLabelModel autoRotationEnabled="false" defaultAngle="0.0" defaultDistance="10.0"/></y:LabelModel><y:ModelParameter><y:SmartEdgeLabelModelParameter angle="6.283185307179586" distance="18.74170057351634" distanceToCenter="true" position="left" ratio="-0.656517644195484" segment="-1"/></y:ModelParameter><y:PreferredPlacementDescriptor angle="0.0" angleOffsetOnRightSide="0" angleReference="absolute" angleRotationOnRightSide="co" distance="-1.0" frozen="true" placement="anywhere" side="anywhere" sideReference="relative_to_edge_flow"/></y:EdgeLabel>
          <y:BendStyle smoothed="false"/>
        </y:PolyLineEdge>
      </data>
    </edge>
    <edge id="e7" source="n4" target="n1">
      <data key="d8" xml:space="preserve"/>
      <data key="d9"/>
      <data key="d10">
        <y:PolyLineEdge>
          <y:Path sx="0.0" sy="0.0" tx="0.0" ty="0.0">
            <y:Point x="414.0" y="97.0"/>
          </y:Path>
          <y:LineStyle color="#000000" type="line" width="1.0"/>
          <y:Arrows source="none" target="delta"/>
          <y:EdgeLabel alignment="center" configuration="AutoFlippingLabel" distance="2.0" fontFamily="Dialog" fontSize="12" fontStyle="plain" hasBackgroundColor="false" hasLineColor="false" height="18.701171875" horizontalTextPosition="center" iconTextGap="4" modelName="custom" preferredPlacement="anywhere" ratio="0.5" textColor="#000000" verticalTextPosition="bottom" visible="true" width="64.703125" x="-115.73242374156894" xml:space="preserve" y="-53.40331291914329">eroga resto<y:LabelModel><y:SmartEdgeLabelModel autoRotationEnabled="false" defaultAngle="0.0" defaultDistance="10.0"/></y:LabelModel><y:ModelParameter><y:SmartEdgeLabelModelParameter angle="6.283185307179586" distance="15.610611953092857" distanceToCenter="true" position="right" ratio="-2.718535864865946" segment="-1"/></y:ModelParameter><y:PreferredPlacementDescriptor angle="0.0" angleOffsetOnRightSide="0" angleReference="absolute" angleRotationOnRightSide="co" distance="-1.0" frozen="true" placement="anywhere" side="anywhere" sideReference="relative_to_edge_flow"/></y:EdgeLabel>
          <y:BendStyle smoothed="false"/>
        </y:PolyLineEdge>
      </data>
    </edge>
    <edge id="e8" source="n2" target="n5">
      <data key="d8" xml:space="preserve"/>
      <data key="d9"/>
      <data key="d10">
        <y:PolyLineEdge>
          <y:Path sx="0.0" sy="0.0" tx="0.0" ty="0.0"/>
          <y:LineStyle color="#000000" type="line" width="1.0"/>
          <y:Arrows source="none" target="delta"/>
          <y:EdgeLabel alignment="center" configuration="AutoFlippingLabel" distance="2.0" fontFamily="Dialog" fontSize="12" fontStyle="plain" hasBackgroundColor="false" hasLineColor="false" height="18.701171875" horizontalTextPosition="center" iconTextGap="4" modelName="custom" preferredPlacement="anywhere" ratio="0.5" textColor="#000000" verticalTextPosition="bottom" visible="true" width="117.390625" x="-124.69532267252612" xml:space="preserve" y="40.1448974609375">inserimento chiavetta<y:LabelModel><y:SmartEdgeLabelModel autoRotationEnabled="false" defaultAngle="0.0" defaultDistance="10.0"/></y:LabelModel><y:ModelParameter><y:SmartEdgeLabelModelParameter angle="6.283185307179586" distance="66.0" distanceToCenter="true" position="right" ratio="0.48616851716778775" segment="-1"/></y:ModelParameter><y:PreferredPlacementDescriptor angle="0.0" angleOffsetOnRightSide="0" angleReference="absolute" angleRotationOnRightSide="co" distance="-1.0" frozen="true" placement="anywhere" side="anywhere" sideReference="relative_to_edge_flow"/></y:EdgeLabel>
          <y:BendStyle smoothed="false"/>
        </y:PolyLineEdge>
      </data>
    </edge>
    <edge id="e9" source="n5" target="n1">
      <data key="d8" xml:space="preserve"/>
      <data key="d9"/>
      <data key="d10">
        <y:PolyLineEdge>
          <y:Path sx="0.0" sy="0.0" tx="0.0" ty="0.0">
            <y:Point x="85.6666666666666" y="396.5"/>
            <y:Point x="85.6666666666666" y="191.0"/>
          </y:Path>
          <y:LineStyle color="#000000" type="line" width="1.0"/>
          <y:Arrows source="none" target="delta"/>
          <y:EdgeLabel alignment="center" configuration="AutoFlippingLabel" distance="2.0" fontFamily="Dialog" fontSize="12" fontStyle="plain" hasBackgroundColor="false" hasLineColor="false" height="33.40234375" horizontalTextPosition="center" iconTextGap="4" modelName="custom" preferredPlacement="anywhere" ratio="0.5" textColor="#000000" verticalTextPosition="bottom" visible="true" width="220.802734375" x="-239.26864115397143" xml:space="preserve" y="7.298828125000227">credito sufficiente, pagamento effettuato,
scala costo<y:LabelModel><y:SmartEdgeLabelModel autoRotationEnabled="false" defaultAngle="0.0" defaultDistance="10.0"/></y:LabelModel><y:ModelParameter><y:SmartEdgeLabelModelParameter angle="6.283185307179586" distance="24.000000000000227" distanceToCenter="true" position="left" ratio="0.5236453201970445" segment="0"/></y:ModelParameter><y:PreferredPlacementDescriptor angle="0.0" angleOffsetOnRightSide="0" angleReference="absolute" angleRotationOnRightSide="co" distance="-1.0" frozen="true" placement="anywhere" side="anywhere" sideReference="relative_to_edge_flow"/></y:EdgeLabel>
          <y:BendStyle smoothed="false"/>
        </y:PolyLineEdge>
      </data>
    </edge>
    <edge id="e10" source="n5" target="n2">
      <data key="d8" xml:space="preserve"/>
      <data key="d9"/>
      <data key="d10">
        <y:PolyLineEdge>
          <y:Path sx="0.0" sy="0.0" tx="0.0" ty="0.0">
            <y:Point x="364.0" y="396.5"/>
            <y:Point x="364.0" y="298.0"/>
          </y:Path>
          <y:LineStyle color="#000000" type="line" width="1.0"/>
          <y:Arrows source="none" target="delta"/>
          <y:EdgeLabel alignment="center" configuration="AutoFlippingLabel" distance="2.0" fontFamily="Dialog" fontSize="12" fontStyle="plain" hasBackgroundColor="false" hasLineColor="false" height="18.701171875" horizontalTextPosition="center" iconTextGap="4" modelName="custom" preferredPlacement="anywhere" ratio="0.5" textColor="#000000" verticalTextPosition="bottom" visible="true" width="106.720703125" x="15.79393513997394" xml:space="preserve" y="7.6494140625">credito insufficiente<y:LabelModel><y:SmartEdgeLabelModel autoRotationEnabled="false" defaultAngle="0.0" defaultDistance="10.0"/></y:LabelModel><y:ModelParameter><y:SmartEdgeLabelModelParameter angle="6.283185307179586" distance="17.0" distanceToCenter="true" position="right" ratio="4.958333333333314" segment="-3"/></y:ModelParameter><y:PreferredPlacementDescriptor angle="0.0" angleOffsetOnRightSide="0" angleReference="absolute" angleRotationOnRightSide="co" distance="-1.0" frozen="true" placement="anywhere" side="anywhere" sideReference="relative_to_edge_flow"/></y:EdgeLabel>
          <y:BendStyle smoothed="false"/>
        </y:PolyLineEdge>
      </data>
    </edge>
  </graph>
  <data key="d7">
    <y:Resources/>
  </data>
</graphml>
